{
    "swagger": "2.0",
    "info": {
        "description": "API for managing timesheets",
        "title": "Timesheet APP",
        "contact": {
            "name": "Udaykishore Resu",
            "email": "udaykishoresu2@gmail.com"
        },
        "license": {
            "name": "MIT"
        },
        "version": "1.0"
    },
    "host": "localhost:8080",
    "basePath": "/",
    "paths": {
      "/login": {
        "post": {
          "summary": "User login",
          "description": "Authenticates a user and returns a JWT token upon successful login.",
          "parameters": [
            {
              "name": "credentials",
              "in": "body",
              "required": true,
              "schema": {
                "type": "object",
                "properties": {
                  "username": { "type": "string" },
                  "password": { "type": "string" }
                }
              }
            }
          ],
          "responses": {
            "200": {
              "description": "JWT token",
              "schema": {
                "type": "object",
                "properties": {
                  "token": { "type": "string", "example": "eyJhbGciOiJIUzI1NiIs..." }
                }
              }
            },
            "400": { "description": "Invalid request payload" },
            "401": { "description": "Invalid username or password" }
          }
        }
      },
      "/projects": {
        "get": {
          "summary": "Retrieve all projects",
          "description": "Fetches the list of available projects.",
          "responses": {
            "200": {
              "description": "List of projects",
              "schema": {
                "type": "array",
                "items": {
                  "type": "object",
                  "properties": {
                    "project_id": { "type": "integer", "example": 1 },
                    "project_name": { "type": "string", "example": "Website Redesign" }
                  }
                }
              }
            },
            "500": { "description": "Internal Server Error" }
          }
        }
      },
      "/subprojects": {
        "get": {
          "summary": "Retrieve subprojects by project ID",
          "description": "Fetches the list of subprojects associated with a specified project ID.",
          "parameters": [
            {
              "name": "project_id",
              "in": "query",
              "required": true,
              "type": "integer",
              "description": "ID of the project"
            }
          ],
          "responses": {
            "200": {
              "description": "List of subprojects",
              "schema": {
                "type": "array",
                "items": {
                  "type": "object",
                  "properties": {
                    "sub_project_id": { "type": "integer", "example": 1 },
                    "sub_project_name": { "type": "string", "example": "Homepage Redesign" },
                    "project_id": { "type": "integer", "example": 1 }
                  }
                }
              }
            },
            "400": { "description": "Invalid project ID" },
            "500": { "description": "Could not retrieve subprojects" }
          }
        }
      },
      "/timesheet": {
        "post": {
          "summary": "Submit a timesheet",
          "description": "Submits a new timesheet for processing and storage.",
          "parameters": [
            {
              "name": "timesheet",
              "in": "body",
              "required": true,
              "schema": {
                "type": "object",
                "properties": {
                  "id": { "type": "integer", "example": 1 },
                  "details": { "type": "string", "example": "Timesheet data" }
                }
              }
            }
          ],
          "responses": {
            "200": {
              "description": "Timesheet submitted successfully",
              "schema": {
                "type": "object",
                "properties": {
                  "message": { "type": "string", "example": "Timesheet submitted successfully" }
                }
              }
            },
            "400": { "description": "Invalid request payload" },
            "500": { "description": "Could not save timesheet" }
          }
        }
      }
    }
  }
  